pyask/__init__.py
pyask/ask.py
pyask/numeric.py
pyask/path.py
pyask/selection.py
pyask/string.py
pyask/utils.py
pyask-0.1.10.dist-info/LICENSE.txt
pyask-0.1.10.dist-info/WHEEL
pyask-0.1.10.dist-info/METADATA
pyask-0.1.10.dist-info/RECORD
