Metadata-Version: 2.1
Name: pyask
Version: 0.1.10
Summary: Library for terminal programs to ask users questions.
Home-page: https://github.com/tmward/pyask
License: ISC
Author: Thomas M Ward
Author-email: thomas@thomasward.com
Requires-Python: >=3.6,<4.0
Classifier: License :: OSI Approved
Classifier: Programming Language :: Python :: 3
Classifier: Programming Language :: Python :: 3.6
Classifier: Programming Language :: Python :: 3.7
Classifier: Programming Language :: Python :: 3.8
Project-URL: Repository, https://github.com/tmward/pyask
